<?xml version="1.0" encoding="UTF-8" ?>
<odoo>
    <data>

        <record id="def1" model="gest_diss.curso">
            <field name="data_hora">29-05-2021 02:02:08</field>
            <field name="local">virtual</field>
            <field name="sala">www.url.com</field>
        </record>

        <record id="def2" model="gest_diss.curso">
            <field name="data_hora">30-05-2021 02:02:08</field>
            <field name="local">presencial</field>
            <field name="sala">sala1</field>
        </record>

        <record id="def3" model="gest_diss.curso">
            <field name="data_hora">24-05-2021 02:02:08</field>
            <field name="local">virtual</field>
            <field name="sala">www.url2.com</field>
        </record>

    </data>
</odoo>